nexus1000v/__init__.py
nexus1000v/nexus1000v.py
nexus1000v-1.7.dist-info/LICENSE
nexus1000v-1.7.dist-info/METADATA
nexus1000v-1.7.dist-info/WHEEL
nexus1000v-1.7.dist-info/top_level.txt
nexus1000v-1.7.dist-info/RECORD
