Metadata-Version: 2.1
Name: nexus1000v
Version: 1.7
Summary: Package to perform operations on Cisco Nexus 1000v
Home-page: https://github.com/vinaypillutla/nexus1000v.git
Author: Vinay Pillutla
Author-email: vinaypillutla@yahoo.in
License: UNKNOWN
Platform: UNKNOWN
Classifier: Programming Language :: Python :: 3
Classifier: Operating System :: OS Independent
